polars_ds_dg-0.4.6.dist-info/METADATA
polars_ds_dg-0.4.6.dist-info/WHEEL
polars_ds_dg-0.4.6.dist-info/license_files/LICENSE.txt
polars_ds/config.py
polars_ds/_utils.py
polars_ds/graph.py
polars_ds/sample.py
polars_ds/type_alias.py
polars_ds/pipeline.py
polars_ds/__init__.py
polars_ds/diagnosis.py
polars_ds/complex.py
polars_ds/stats.py
polars_ds/transforms.py
polars_ds/metrics.py
polars_ds/str2.py
polars_ds/num.py
polars_ds/_polars_ds.abi3.so
polars_ds_dg-0.4.6.dist-info/RECORD
