Metadata-Version: 2.3
Name: polars_ds_dg
Version: 0.4.6
Classifier: Development Status :: 4 - Beta
Classifier: Programming Language :: Rust
Classifier: Programming Language :: Python :: Implementation :: CPython
Classifier: Programming Language :: Python :: Implementation :: PyPy
Classifier: License :: OSI Approved :: MIT License
Requires-Dist: polars >=0.20.6, !=0.20.12
Requires-Dist: typing-extensions ; python_version <= '3.11'
Requires-Dist: great-tables >=0.5 ; extra == 'plot'
Requires-Dist: graphviz >=0.20 ; extra == 'plot'
Requires-Dist: plotly >=5.0, <6 ; extra == 'plot'
Provides-Extra: plot
License-File: LICENSE.txt
Keywords: polars-extension,scientific-computing,data-science
Author-email: Tianren Qin <tq9695@gmail.com>
Requires-Python: >=3.8
